cli/__init__.py
cli/__main__.py
cli/config.py
cli/export.py
cli/export_eln_website_utils.py
cli/export_utils.py
cli/fetch.py
cli/register.py
cli/stockscli.ini
cli/utils.py
cli/validate.py
stocks/__init__.py
stocks/models.py
stocks/assaysniffer/__init__.py
stocks/assaysniffer/registry.py
stocks/assaysniffer/sniffers.py
stocks_cli-0.3.1.data/data/cli/stockscli.ini
stocksapi/__init__.py
stocksapi/client.py
stocksapi/exceptions.py
stocksapi/manager.py
stocksapi/models.py
stocks_cli-0.3.1.dist-info/LICENSE.txt
stocks_cli-0.3.1.dist-info/METADATA
stocks_cli-0.3.1.dist-info/WHEEL
stocks_cli-0.3.1.dist-info/entry_points.txt
stocks_cli-0.3.1.dist-info/top_level.txt
stocks_cli-0.3.1.dist-info/RECORD
